<?xml version="1.0" encoding="UTF-8" standalone="yes"?>
<dgm:dataModel xmlns:dgm="http://schemas.openxmlformats.org/drawingml/2006/diagram" xmlns:a="http://schemas.openxmlformats.org/drawingml/2006/main"><dgm:ptLst><dgm:pt modelId="{6A1812C9-625E-4000-92BE-42A910CD8280}" type="doc"><dgm:prSet loTypeId="urn:microsoft.com/office/officeart/2005/8/layout/vList2" loCatId="list" qsTypeId="urn:microsoft.com/office/officeart/2005/8/quickstyle/simple1" qsCatId="simple" csTypeId="urn:microsoft.com/office/officeart/2005/8/colors/accent2_2" csCatId="accent2" phldr="1"/><dgm:spPr/><dgm:t><a:bodyPr/><a:lstStyle/><a:p><a:endParaRPr lang="en-US"/></a:p></dgm:t></dgm:pt><dgm:pt modelId="{DB7ECF28-BD45-034F-8DE1-0CD34B2466E2}"><dgm:prSet custT="1"/><dgm:spPr/><dgm:t><a:bodyPr/><a:lstStyle/><a:p><a:pPr algn="l"><a:lnSpc><a:spcPct val="90000"/></a:lnSpc></a:pPr><a:r><a:rPr lang="en-US" sz="1600" b="0" i="0" dirty="0"><a:solidFill><a:schemeClr val="tx1"/></a:solidFill></a:rPr><a:t>Network connectivity is improving (4G/5G) but remains inconsistent; power outages are common.</a:t></a:r><a:endParaRPr lang="en-GB" sz="1600" dirty="0"><a:solidFill><a:schemeClr val="tx1"/></a:solidFill><a:latin typeface="Calibri"/><a:ea typeface="+mn-ea"/><a:cs typeface="+mn-cs"/></a:endParaRPr></a:p></dgm:t></dgm:pt><dgm:pt modelId="{ACFA9542-9927-C541-9118-024F49BB5B46}" type="parTrans" cxnId="{8DCFFF49-6268-3E49-9E1B-5F208B9E042E}"><dgm:prSet/><dgm:spPr/><dgm:t><a:bodyPr/><a:lstStyle/><a:p><a:endParaRPr lang="en-GB" sz="1600"><a:solidFill><a:schemeClr val="tx1"/></a:solidFill></a:endParaRPr></a:p></dgm:t></dgm:pt><dgm:pt modelId="{15458004-0B22-F644-8CE1-B2271F958023}" type="sibTrans" cxnId="{8DCFFF49-6268-3E49-9E1B-5F208B9E042E}"><dgm:prSet/><dgm:spPr/><dgm:t><a:bodyPr/><a:lstStyle/><a:p><a:endParaRPr lang="en-GB" sz="1600"><a:solidFill><a:schemeClr val="tx1"/></a:solidFill></a:endParaRPr></a:p></dgm:t></dgm:pt><dgm:pt modelId="{2ECDDF74-98EF-834B-9794-F16B0059244A}"><dgm:prSet custT="1"/><dgm:spPr/><dgm:t><a:bodyPr/><a:lstStyle/><a:p><a:pPr algn="l" rtl="0"><a:lnSpc><a:spcPct val="90000"/></a:lnSpc></a:pPr><a:r><a:rPr lang="en-US" sz="1600" b="0" i="0" dirty="0"><a:solidFill><a:schemeClr val="tx1"/></a:solidFill></a:rPr><a:t>Patients often struggle to describe symptoms accurately to remote doctors due to dialect differences.</a:t></a:r></a:p></dgm:t></dgm:pt><dgm:pt modelId="{377D22AD-E2ED-1041-A86F-17898C543141}" type="parTrans" cxnId="{A9AFFC91-9A1F-B744-A625-B181460A3E7D}"><dgm:prSet/><dgm:spPr/><dgm:t><a:bodyPr/><a:lstStyle/><a:p><a:endParaRPr lang="en-GB" sz="1600"><a:solidFill><a:schemeClr val="tx1"/></a:solidFill></a:endParaRPr></a:p></dgm:t></dgm:pt><dgm:pt modelId="{BC388C10-8787-424C-893D-8D0ADD0E1609}" type="sibTrans" cxnId="{A9AFFC91-9A1F-B744-A625-B181460A3E7D}"><dgm:prSet/><dgm:spPr/><dgm:t><a:bodyPr/><a:lstStyle/><a:p><a:endParaRPr lang="en-GB" sz="1600"><a:solidFill><a:schemeClr val="tx1"/></a:solidFill></a:endParaRPr></a:p></dgm:t></dgm:pt><dgm:pt modelId="{2BF3BBDF-1E53-FA4A-89DC-211AD4EA42C9}"><dgm:prSet custT="1"/><dgm:spPr/><dgm:t><a:bodyPr/><a:lstStyle/><a:p><a:pPr algn="l"><a:lnSpc><a:spcPct val="90000"/></a:lnSpc></a:pPr><a:r><a:rPr lang="en-US" sz="1600" b="0" i="0" dirty="0"><a:solidFill><a:schemeClr val="tx1"/></a:solidFill></a:rPr><a:t>Trust is physical; patients prefer an assisted model (Kiosk) over a pure DIY app.</a:t></a:r></a:p></dgm:t></dgm:pt><dgm:pt modelId="{57380FAC-ED79-C342-A71C-2213D2923BF6}" type="parTrans" cxnId="{9CAA1294-F8C6-0540-B0F8-B7F9F262D349}"><dgm:prSet/><dgm:spPr/><dgm:t><a:bodyPr/><a:lstStyle/><a:p><a:endParaRPr lang="en-GB" sz="1600"><a:solidFill><a:schemeClr val="tx1"/></a:solidFill></a:endParaRPr></a:p></dgm:t></dgm:pt><dgm:pt modelId="{8BD3DDE0-A1FC-AF47-AD5B-5605A88E2175}" type="sibTrans" cxnId="{9CAA1294-F8C6-0540-B0F8-B7F9F262D349}"><dgm:prSet/><dgm:spPr/><dgm:t><a:bodyPr/><a:lstStyle/><a:p><a:endParaRPr lang="en-GB" sz="1600"><a:solidFill><a:schemeClr val="tx1"/></a:solidFill></a:endParaRPr></a:p></dgm:t></dgm:pt><dgm:pt modelId="{EC8DF089-46BB-48C6-8F98-1FDB113F3803}"><dgm:prSet phldr="0" custT="1"/><dgm:spPr/><dgm:t><a:bodyPr/><a:lstStyle/><a:p><a:pPr algn="l" rtl="0"><a:lnSpc><a:spcPct val="90000"/></a:lnSpc></a:pPr><a:r><a:rPr lang="en-US" sz="1600" b="0" i="0" dirty="0"><a:solidFill><a:schemeClr val="tx1"/></a:solidFill></a:rPr><a:t>Tier-2/3 cities and villages suffer from a severe shortage of qualified doctors.</a:t></a:r><a:endParaRPr lang="en-GB" sz="1600" dirty="0"><a:solidFill><a:schemeClr val="tx1"/></a:solidFill><a:latin typeface="Calibri"/><a:ea typeface="+mn-ea"/><a:cs typeface="+mn-cs"/></a:endParaRPr></a:p></dgm:t></dgm:pt><dgm:pt modelId="{20B779C7-65DE-42D4-8945-02540CF968B4}" type="parTrans" cxnId="{E43AEDA4-E00C-42D6-BAF5-B7AF1C573564}"><dgm:prSet/><dgm:spPr/><dgm:t><a:bodyPr/><a:lstStyle/><a:p><a:endParaRPr lang="en-US"/></a:p></dgm:t></dgm:pt><dgm:pt modelId="{8ED70207-8F2E-4B0C-914D-E5501216F976}" type="sibTrans" cxnId="{E43AEDA4-E00C-42D6-BAF5-B7AF1C573564}"><dgm:prSet/><dgm:spPr/><dgm:t><a:bodyPr/><a:lstStyle/><a:p><a:endParaRPr lang="en-US"/></a:p></dgm:t></dgm:pt><dgm:pt modelId="{F84AB389-3374-4A63-832B-A3879EA694C8}" type="pres"><dgm:prSet presAssocID="{6A1812C9-625E-4000-92BE-42A910CD8280}" presName="linear" presStyleCnt="0"><dgm:presLayoutVars><dgm:animLvl val="lvl"/><dgm:resizeHandles val="exact"/></dgm:presLayoutVars></dgm:prSet><dgm:spPr/></dgm:pt><dgm:pt modelId="{D56A9292-5989-45F0-9802-9B8FB36FC2F5}" type="pres"><dgm:prSet presAssocID="{EC8DF089-46BB-48C6-8F98-1FDB113F3803}" presName="parentText" presStyleLbl="node1" presStyleIdx="0" presStyleCnt="4"><dgm:presLayoutVars><dgm:chMax val="0"/><dgm:bulletEnabled val="1"/></dgm:presLayoutVars></dgm:prSet><dgm:spPr/></dgm:pt><dgm:pt modelId="{AF30246B-DBED-4DF8-9DA7-7AD5DE79470C}" type="pres"><dgm:prSet presAssocID="{8ED70207-8F2E-4B0C-914D-E5501216F976}" presName="spacer" presStyleCnt="0"/><dgm:spPr/></dgm:pt><dgm:pt modelId="{ABE93F0F-BBDF-A44F-BBD0-795651582C71}" type="pres"><dgm:prSet presAssocID="{DB7ECF28-BD45-034F-8DE1-0CD34B2466E2}" presName="parentText" presStyleLbl="node1" presStyleIdx="1" presStyleCnt="4"><dgm:presLayoutVars><dgm:chMax val="0"/><dgm:bulletEnabled val="1"/></dgm:presLayoutVars></dgm:prSet><dgm:spPr/></dgm:pt><dgm:pt modelId="{1A7FE23B-C8D9-B245-B4E7-1ACC8C3F909F}" type="pres"><dgm:prSet presAssocID="{15458004-0B22-F644-8CE1-B2271F958023}" presName="spacer" presStyleCnt="0"/><dgm:spPr/></dgm:pt><dgm:pt modelId="{E4708D60-1A13-5346-A61C-07FFBCB520B8}" type="pres"><dgm:prSet presAssocID="{2ECDDF74-98EF-834B-9794-F16B0059244A}" presName="parentText" presStyleLbl="node1" presStyleIdx="2" presStyleCnt="4"><dgm:presLayoutVars><dgm:chMax val="0"/><dgm:bulletEnabled val="1"/></dgm:presLayoutVars></dgm:prSet><dgm:spPr/></dgm:pt><dgm:pt modelId="{CB0EBF1B-542A-3243-9941-12049413A7F1}" type="pres"><dgm:prSet presAssocID="{BC388C10-8787-424C-893D-8D0ADD0E1609}" presName="spacer" presStyleCnt="0"/><dgm:spPr/></dgm:pt><dgm:pt modelId="{B2084E37-06BD-7E4D-A770-070CDCC36D4D}" type="pres"><dgm:prSet presAssocID="{2BF3BBDF-1E53-FA4A-89DC-211AD4EA42C9}" presName="parentText" presStyleLbl="node1" presStyleIdx="3" presStyleCnt="4"><dgm:presLayoutVars><dgm:chMax val="0"/><dgm:bulletEnabled val="1"/></dgm:presLayoutVars></dgm:prSet><dgm:spPr/></dgm:pt></dgm:ptLst><dgm:cxnLst><dgm:cxn modelId="{FBAC1D14-4E52-49FA-9458-F2A1A106896D}" type="presOf" srcId="{2ECDDF74-98EF-834B-9794-F16B0059244A}" destId="{E4708D60-1A13-5346-A61C-07FFBCB520B8}" srcOrd="0" destOrd="0" presId="urn:microsoft.com/office/officeart/2005/8/layout/vList2"/><dgm:cxn modelId="{8DCFFF49-6268-3E49-9E1B-5F208B9E042E}" srcId="{6A1812C9-625E-4000-92BE-42A910CD8280}" destId="{DB7ECF28-BD45-034F-8DE1-0CD34B2466E2}" srcOrd="1" destOrd="0" parTransId="{ACFA9542-9927-C541-9118-024F49BB5B46}" sibTransId="{15458004-0B22-F644-8CE1-B2271F958023}"/><dgm:cxn modelId="{433B057D-7119-4DDA-9CA1-C94EFBA05FDB}" type="presOf" srcId="{DB7ECF28-BD45-034F-8DE1-0CD34B2466E2}" destId="{ABE93F0F-BBDF-A44F-BBD0-795651582C71}" srcOrd="0" destOrd="0" presId="urn:microsoft.com/office/officeart/2005/8/layout/vList2"/><dgm:cxn modelId="{A9AFFC91-9A1F-B744-A625-B181460A3E7D}" srcId="{6A1812C9-625E-4000-92BE-42A910CD8280}" destId="{2ECDDF74-98EF-834B-9794-F16B0059244A}" srcOrd="2" destOrd="0" parTransId="{377D22AD-E2ED-1041-A86F-17898C543141}" sibTransId="{BC388C10-8787-424C-893D-8D0ADD0E1609}"/><dgm:cxn modelId="{9CAA1294-F8C6-0540-B0F8-B7F9F262D349}" srcId="{6A1812C9-625E-4000-92BE-42A910CD8280}" destId="{2BF3BBDF-1E53-FA4A-89DC-211AD4EA42C9}" srcOrd="3" destOrd="0" parTransId="{57380FAC-ED79-C342-A71C-2213D2923BF6}" sibTransId="{8BD3DDE0-A1FC-AF47-AD5B-5605A88E2175}"/><dgm:cxn modelId="{492E009B-114D-43EE-8503-61841AE8D5EB}" type="presOf" srcId="{2BF3BBDF-1E53-FA4A-89DC-211AD4EA42C9}" destId="{B2084E37-06BD-7E4D-A770-070CDCC36D4D}" srcOrd="0" destOrd="0" presId="urn:microsoft.com/office/officeart/2005/8/layout/vList2"/><dgm:cxn modelId="{E43AEDA4-E00C-42D6-BAF5-B7AF1C573564}" srcId="{6A1812C9-625E-4000-92BE-42A910CD8280}" destId="{EC8DF089-46BB-48C6-8F98-1FDB113F3803}" srcOrd="0" destOrd="0" parTransId="{20B779C7-65DE-42D4-8945-02540CF968B4}" sibTransId="{8ED70207-8F2E-4B0C-914D-E5501216F976}"/><dgm:cxn modelId="{EDDB50DF-FA87-43E6-A9E8-0D1A052F2F57}" type="presOf" srcId="{6A1812C9-625E-4000-92BE-42A910CD8280}" destId="{F84AB389-3374-4A63-832B-A3879EA694C8}" srcOrd="0" destOrd="0" presId="urn:microsoft.com/office/officeart/2005/8/layout/vList2"/><dgm:cxn modelId="{F50F68FE-812D-46B1-A079-39BEF0C671A5}" type="presOf" srcId="{EC8DF089-46BB-48C6-8F98-1FDB113F3803}" destId="{D56A9292-5989-45F0-9802-9B8FB36FC2F5}" srcOrd="0" destOrd="0" presId="urn:microsoft.com/office/officeart/2005/8/layout/vList2"/><dgm:cxn modelId="{268FF10E-24B7-421F-B7AC-5DB821932E17}" type="presParOf" srcId="{F84AB389-3374-4A63-832B-A3879EA694C8}" destId="{D56A9292-5989-45F0-9802-9B8FB36FC2F5}" srcOrd="0" destOrd="0" presId="urn:microsoft.com/office/officeart/2005/8/layout/vList2"/><dgm:cxn modelId="{4E985043-31CD-4F99-AA86-0A897D020276}" type="presParOf" srcId="{F84AB389-3374-4A63-832B-A3879EA694C8}" destId="{AF30246B-DBED-4DF8-9DA7-7AD5DE79470C}" srcOrd="1" destOrd="0" presId="urn:microsoft.com/office/officeart/2005/8/layout/vList2"/><dgm:cxn modelId="{EAB3857C-72C7-4558-AC52-DD13A0E52466}" type="presParOf" srcId="{F84AB389-3374-4A63-832B-A3879EA694C8}" destId="{ABE93F0F-BBDF-A44F-BBD0-795651582C71}" srcOrd="2" destOrd="0" presId="urn:microsoft.com/office/officeart/2005/8/layout/vList2"/><dgm:cxn modelId="{BBFC9794-5D9D-4544-9E04-452C872809DC}" type="presParOf" srcId="{F84AB389-3374-4A63-832B-A3879EA694C8}" destId="{1A7FE23B-C8D9-B245-B4E7-1ACC8C3F909F}" srcOrd="3" destOrd="0" presId="urn:microsoft.com/office/officeart/2005/8/layout/vList2"/><dgm:cxn modelId="{E8EDA29F-F787-4593-818C-63BE01EA8E36}" type="presParOf" srcId="{F84AB389-3374-4A63-832B-A3879EA694C8}" destId="{E4708D60-1A13-5346-A61C-07FFBCB520B8}" srcOrd="4" destOrd="0" presId="urn:microsoft.com/office/officeart/2005/8/layout/vList2"/><dgm:cxn modelId="{323DF320-0C96-445C-B91F-42C7C3A53A5A}" type="presParOf" srcId="{F84AB389-3374-4A63-832B-A3879EA694C8}" destId="{CB0EBF1B-542A-3243-9941-12049413A7F1}" srcOrd="5" destOrd="0" presId="urn:microsoft.com/office/officeart/2005/8/layout/vList2"/><dgm:cxn modelId="{2C348207-E1CE-4AB3-9347-2B6B27ADF362}" type="presParOf" srcId="{F84AB389-3374-4A63-832B-A3879EA694C8}" destId="{B2084E37-06BD-7E4D-A770-070CDCC36D4D}" srcOrd="6" destOrd="0" presId="urn:microsoft.com/office/officeart/2005/8/layout/vList2"/></dgm:cxnLst><dgm:bg/><dgm:whole/><dgm:extLst><a:ext uri="http://schemas.microsoft.com/office/drawing/2008/diagram"><dsp:dataModelExt xmlns:dsp="http://schemas.microsoft.com/office/drawing/2008/diagram" relId="rId7" minVer="http://schemas.openxmlformats.org/drawingml/2006/diagram"/></a:ext></dgm:extLst></dgm:dataModel>